README.rst
setup.cfg
setup.py
django_geopositionmap.egg-info/PKG-INFO
django_geopositionmap.egg-info/SOURCES.txt
django_geopositionmap.egg-info/dependency_links.txt
django_geopositionmap.egg-info/not-zip-safe
django_geopositionmap.egg-info/requires.txt
django_geopositionmap.egg-info/top_level.txt
geopositionmap/__init__.py
geopositionmap/conf.py
geopositionmap/errors.py
geopositionmap/geoFields.py
geopositionmap/geoFormFields.py
geopositionmap/geoManager.py
geopositionmap/geoModels.py
geopositionmap/geoWidgets.py
geopositionmap/manage.py
geopositionmap/example/__init__.py
geopositionmap/example/admin.py
geopositionmap/example/models.py
geopositionmap/example/tests.py
geopositionmap/example/views.py
geopositionmap/static/geopositionmap/geopositionmap.css
geopositionmap/static/geopositionmap/geopositionmap.js
geopositionmap/templates/geopositionmap/widgets/geopositionmap.html
geopositionmap/tests/__init__.py
geopositionmap/tests/settings.py
geopositionmap/tests/test_geoposition.py
geopositionmap/tests/urls.py