Metadata-Version: 1.1
Name: django-geopositionmap
Version: 1.0.0
Summary: Django Geoposition, google and osm map. Model field that can hold a geoposition with bound method, gis Point type, and corresponding admin widget.
Home-page: http://github.com/ivandm/django-geopositionmap
Author: Ivan Del Mastro
Author-email: info@adventure2italy.com
License: UNKNOWN
Platform: UNKNOWN
Classifier: Development Status :: 5 - Production/Stable
Classifier: Environment :: Web Environment
Classifier: Intended Audience :: Developers
Classifier: License :: OSI Approved :: BSD License
Classifier: Operating System :: OS Independent
Classifier: Programming Language :: Python
Classifier: Framework :: Django
